V4/ApiMonitor.py
V4/ArtGenSys.py
V4/ConfigManager.py
V4/FloraDatabase.py
V4/FloraWikipediaScraper.py
V4/RagSys.py
V4/Spider.py
V4/UniversalArticleGenerator.py
V4/__init__.py
V4/cli.py
V4/main.py
V4/setup_v4.py
V4/test_v4.py
V4/utils.py
V4/config/ai_settings.json
V4/config/api_monitor.json
V4/config/article_config.json
V4/config/article_config_universal.json
V4/config/config.json
V4/config/domain_reliability.json
V4/config/domains.json
V4/config/search_config.json
V4/config/universal_article_config.json
viincci_rag/__init__.py
viincci_rag-2.0.0.dist-info/licenses/LICENSE
viincci_rag-2.0.0.dist-info/METADATA
viincci_rag-2.0.0.dist-info/WHEEL
viincci_rag-2.0.0.dist-info/entry_points.txt
viincci_rag-2.0.0.dist-info/top_level.txt
viincci_rag-2.0.0.dist-info/RECORD
