Metadata-Version: 2.4
Name: viincci-rag
Version: 2.0.0
Summary: Universal multi-domain research system with RAG (Retrieval-Augmented Generation) capabilities
Author-email: MrViincciLeRoy <Viincci@proton.me>
Maintainer-email: MrViincciLeRoy <Viincci@proton.me>
License: MIT
Project-URL: Homepage, https://github.com/viincci/Viincci-RAG
Project-URL: Documentation, https://github.com/viincci/Viincci-RAG
Project-URL: Repository, https://github.com/viincci/Viincci-RAG
Project-URL: Bug Tracker, https://github.com/viincci/Viincci-RAG/issues
Keywords: research,rag,nlp,ai,machine-learning,information-retrieval,multi-domain
Classifier: Development Status :: 4 - Beta
Classifier: Intended Audience :: Science/Research
Classifier: Intended Audience :: Education
Classifier: Topic :: Scientific/Engineering :: Artificial Intelligence
Classifier: Topic :: Scientific/Engineering :: Information Analysis
Classifier: License :: OSI Approved :: MIT License
Classifier: Programming Language :: Python :: 3
Classifier: Programming Language :: Python :: 3.9
Classifier: Programming Language :: Python :: 3.10
Classifier: Programming Language :: Python :: 3.11
Classifier: Operating System :: OS Independent
Requires-Python: >=3.9
License-File: LICENSE
Requires-Dist: requests>=2.31.0
Requires-Dist: beautifulsoup4>=4.12.0
Requires-Dist: lxml>=4.9.0
Requires-Dist: pandas>=2.0.0
Requires-Dist: torch>=2.0.0
Requires-Dist: transformers>=4.35.0
Requires-Dist: sentence-transformers>=2.2.0
Requires-Dist: faiss-cpu>=1.7.4
Requires-Dist: PyPDF2>=3.0.0
Requires-Dist: wikipedia-api>=0.6.0
Provides-Extra: dev
Requires-Dist: pytest>=7.4.0; extra == "dev"
Requires-Dist: pytest-cov>=4.1.0; extra == "dev"
Requires-Dist: pytest-mock>=3.11.0; extra == "dev"
Requires-Dist: flake8>=6.1.0; extra == "dev"
Requires-Dist: black>=23.0.0; extra == "dev"
Provides-Extra: cuda
Requires-Dist: torch>=2.0.0; extra == "cuda"
Provides-Extra: all
Requires-Dist: accelerate>=0.24.0; extra == "all"
Requires-Dist: bitsandbytes>=0.41.0; extra == "all"
Dynamic: license-file
